fn_deps.py
fn_deps-0.1.0.dist-info/entry_points.txt
fn_deps-0.1.0.dist-info/WHEEL
fn_deps-0.1.0.dist-info/METADATA
fn_deps-0.1.0.dist-info/RECORD
