Metadata-Version: 2.1
Name: fn-deps
Version: 0.1.0
Summary: 
Home-page: https://github.com/BusinessOptics/fn_deps
License: MIT
Author: James Saunders
Author-email: james@businessoptics.biz
Requires-Python: >=3.6,<4.0
Classifier: License :: OSI Approved :: MIT License
Classifier: Programming Language :: Python :: 3
Classifier: Programming Language :: Python :: 3.6
Classifier: Programming Language :: Python :: 3.7
Classifier: Programming Language :: Python :: 3.8
Requires-Dist: click (>=7.1.2,<8.0.0)
Requires-Dist: dephell (>=0.8.3,<0.9.0)
Requires-Dist: gitpython (>=3.1.2,<4.0.0)
Requires-Dist: sh (>=1.13.1,<2.0.0)
Project-URL: Repository, https://github.com/BusinessOptics/fn_deps
